mytext/__init__.py
mytext/__main__.py
mytext/functions.py
mytext/params.py
mytext/providers.py
mytext-0.4.dist-info/licenses/AUTHORS.md
mytext-0.4.dist-info/licenses/LICENSE
mytext-0.4.dist-info/METADATA
mytext-0.4.dist-info/WHEEL
mytext-0.4.dist-info/entry_points.txt
mytext-0.4.dist-info/top_level.txt
mytext-0.4.dist-info/RECORD
